README.md
setup.cfg
setup.py
eis/__init__.py
eis/process-manager/__init__.py
eis/process-manager/api_client.py
eis/process-manager/configuration.py
eis/process-manager/exceptions.py
eis/process-manager/model_utils.py
eis/process-manager/rest.py
eis/process-manager/api/__init__.py
eis/process-manager/api/decision_table_versions_api.py
eis/process-manager/api/decision_tables_api.py
eis/process-manager/api/default_api.py
eis/process-manager/api/service_event_api.py
eis/process-manager/api/workflow_instances_api.py
eis/process-manager/api/workflow_versions_api.py
eis/process-manager/api/workflows_api.py
eis/process-manager/apis/__init__.py
eis/process-manager/model/__init__.py
eis/process-manager/model/create_decision_table_response_class.py
eis/process-manager/model/create_workflow_request_dto_rest.py
eis/process-manager/model/create_workflow_request_dto_shared.py
eis/process-manager/model/decision_table_class.py
eis/process-manager/model/decision_table_version_class.py
eis/process-manager/model/decision_table_version_class_without_definition.py
eis/process-manager/model/define_service_event_request_dto.py
eis/process-manager/model/get_decision_table_response_class.py
eis/process-manager/model/get_decision_table_version_response_class.py
eis/process-manager/model/get_workflow_instance_request_dto.py
eis/process-manager/model/get_workflow_instance_response_class.py
eis/process-manager/model/get_workflow_instance_variables_class.py
eis/process-manager/model/get_workflow_request_dto.py
eis/process-manager/model/get_workflow_response_class.py
eis/process-manager/model/get_workflow_version_response_class.py
eis/process-manager/model/inline_response200.py
eis/process-manager/model/inline_response503.py
eis/process-manager/model/list_decision_table_versions_response_class.py
eis/process-manager/model/list_decision_tables_response_class.py
eis/process-manager/model/list_service_event_types_response_class.py
eis/process-manager/model/list_service_events_response_class.py
eis_process_manager.egg-info/PKG-INFO
eis_process_manager.egg-info/SOURCES.txt
eis_process_manager.egg-info/dependency_links.txt
eis_process_manager.egg-info/requires.txt
eis_process_manager.egg-info/top_level.txt
