Metadata-Version: 2.1
Name: eis-process-manager
Version: 1.4.0
Summary: EMIL Process Manager
Home-page: UNKNOWN
Author: Contact us
Author-email: kontakt@emil.de
License: UNKNOWN
Keywords: OpenAPI,OpenAPI-Generator,EMIL Process Manager
Platform: UNKNOWN
Requires-Python: >=3.6
